{
  "authors" : [
    "Fernando Correa de Oliveira"
  ],
  "build-depends" : [ ],
  "depends" : [ ],
  "description" : "A perl6 ORM",
  "license" : "Artistic-2.0",
  "name" : "Red",
  "perl" : "6.c",
  "provides" : {
    "MetamodelX::Red::Model"     : "lib/MetamodelX/Red/Model.pm6",
    "MetamodelX::Red::Comparate" : "lib/MetamodelX/Red/Comparate.pm6",
    "MetamodelX::Red::Relate"    : "lib/MetamodelX/Red/Relate.pm6",
    "Red::AttrColumn"            : "lib/Red/AttrColumn.pm6",
    "Red::Column"                : "lib/Red/Column.pm6",
    "Red::Database"              : "lib/Red/Database.pm6",
    "Red::DefaultResultSeq"      : "lib/Red/DefaultResultSeq.pm6",
    "Red::AST"                   : "lib/Red/Filter.pm6",
    "Red::Model"                 : "lib/Red/Model.pm6",
    "Red::Operators"             : "lib/Red/Operators.pm6",
    "Red::ResultSeq"             : "lib/Red/ResultSeq.pm6",
    "Red::Traits"                : "lib/Red/Traits.pm6",
    "Red::Utils"                 : "lib/Red/Utils.pm6",
    "Red"                        : "lib/Red.pm6"
  },
  "resources" : [ ],
  "source-url" : "",
  "tags" : [ "ORM", "database", "map", "relational" ],
  "test-depends" : [
      "Test::META"
  ],
  "version" : "0.0.1"
}
